lib/__init__.py
lib/sayhellosravanthi.py
sayhellosravanthi-0.0.1.dist-info/METADATA
sayhellosravanthi-0.0.1.dist-info/WHEEL
sayhellosravanthi-0.0.1.dist-info/top_level.txt
sayhellosravanthi-0.0.1.dist-info/RECORD
